door_signs_script/Door_Sign_Script_General.py
door_signs_script/__init__.py
door_signs_script-0.0.9.dist-info/LICENSE.txt
door_signs_script-0.0.9.dist-info/METADATA
door_signs_script-0.0.9.dist-info/WHEEL
door_signs_script-0.0.9.dist-info/top_level.txt
door_signs_script-0.0.9.dist-info/RECORD
